README.rst
setup.py
persistentdicts/__init__.py
persistentdicts/cassandradict.py
persistentdicts/kyotocabinetdict.py
persistentdicts/proxydict.py
persistentdicts/sqlitedict.py
persistentdicts/tests.py
persistentdicts_dev.egg-info/PKG-INFO
persistentdicts_dev.egg-info/SOURCES.txt
persistentdicts_dev.egg-info/dependency_links.txt
persistentdicts_dev.egg-info/requires.txt
persistentdicts_dev.egg-info/top_level.txt