Metadata-Version: 1.1
Name: persistentdicts-dev
Version: 1.2.3.dev6
Summary: development version of persistentdicts
Home-page: https://github.com/chmduquesne/persistentdicts
Author: Christophe-Marie Duquesne
Author-email: chmd@chmd.fr
License: UNKNOWN
Download-URL: https://github.com/chmduquesne/persistentdicts/archive/master.tar.gz
Keywords: database,interface,adapter
Platform: UNKNOWN
Classifier: Development Status :: 4 - Beta
Classifier: Intended Audience :: Developers
Classifier: License :: OSI Approved :: MIT License
Classifier: Operating System :: OS Independent
Classifier: Programming Language :: Python :: 2
